daxa/__init__.py
daxa/_version.py
daxa/config.py
daxa/exceptions.py
daxa/misc.py
daxa/archive/__init__.py
daxa/archive/assemble.py
daxa/archive/base.py
daxa/files/browse_extract.pl
daxa/files/daxa-high-resolution-color-logo.png
daxa/files/daxa-high-resolution-logo-black-on-transparent-background.png
daxa/files/daxa-high-resolution-logo-black-on-white-background.png
daxa/files/erass_de_dr1_info.csv
daxa/files/erosita_calpv_info.csv
daxa/files/sas_errors.csv
daxa/files/sas_warnings.csv
daxa/mission/__init__.py
daxa/mission/asca.py
daxa/mission/base.py
daxa/mission/chandra.py
daxa/mission/erosita.py
daxa/mission/integral.py
daxa/mission/nustar.py
daxa/mission/rosat.py
daxa/mission/suzaku.py
daxa/mission/swift.py
daxa/mission/tools.py
daxa/mission/xmm.py
daxa/mission/xrism.py
daxa/process/__init__.py
daxa/process/_backend_check.py
daxa/process/_cleanup.py
daxa/process/_common.py
daxa/process/simple.py
daxa/process/chandra/__init__.py
daxa/process/chandra/_common.py
daxa/process/chandra/assemble.py
daxa/process/chandra/clean.py
daxa/process/chandra/detect.py
daxa/process/chandra/generate.py
daxa/process/chandra/setup.py
daxa/process/erosita/__init__.py
daxa/process/erosita/_common.py
daxa/process/erosita/assemble.py
daxa/process/erosita/clean.py
daxa/process/erosita/setup.py
daxa/process/general/__init__.py
daxa/process/general/preprocessed.py
daxa/process/nustar/__init__.py
daxa/process/nustar/_common.py
daxa/process/nustar/assemble.py
daxa/process/nustar/clean.py
daxa/process/nustar/generate.py
daxa/process/nustar/setup.py
daxa/process/xmm/__init__.py
daxa/process/xmm/_common.py
daxa/process/xmm/assemble.py
daxa/process/xmm/check.py
daxa/process/xmm/clean.py
daxa/process/xmm/generate.py
daxa/process/xmm/setup.py
daxa-0.3.5.dist-info/licenses/LICENSE
daxa-0.3.5.dist-info/METADATA
daxa-0.3.5.dist-info/WHEEL
daxa-0.3.5.dist-info/top_level.txt
daxa-0.3.5.dist-info/RECORD
