Metadata-Version: 2.4
Name: daxa
Version: 0.3.5
Summary: Democratising Astronomy X-ray Archives (DAXA) is an easy-to-use Python module which enables the simple processing and reduction of archives of X-ray telescope observations.
Home-page: https://github.com/DavidT3/DAXA
Author: David J Turner
Author-email: turne540@msu.edu
License: BSD 3
Requires-Python: >=3.10
License-File: LICENSE
Requires-Dist: numpy>=1.26.4
Requires-Dist: astroquery>=0.4.7
Requires-Dist: pandas>=2.2.2
Requires-Dist: astropy>=6.1.2
Requires-Dist: packaging>=24.1
Requires-Dist: tqdm>=4.66.4
Requires-Dist: exceptiongroup>=1.0.4
Requires-Dist: scipy>=1.14.0
Requires-Dist: tabulate>=0.9.0
Requires-Dist: unlzw3>=0.2.2
Requires-Dist: xga>=0.6.0
Dynamic: author
Dynamic: author-email
Dynamic: description
Dynamic: description-content-type
Dynamic: home-page
Dynamic: license
Dynamic: license-file
Dynamic: requires-dist
Dynamic: requires-python
Dynamic: summary
